ctxpy/__init__.py
ctxpy/base.py
ctxpy/chemical.py
ctxpy/chemical_list.py
ctxpy/command_line.py
ctxpy/exceptions.py
ctxpy/exposure.py
ctxpy/hazard.py
ctxpy/utils.py
ctxpy/data/toxprints.txt
ctx_python-0.0.1a8.dist-info/METADATA
ctx_python-0.0.1a8.dist-info/WHEEL
ctx_python-0.0.1a8.dist-info/entry_points.txt
ctx_python-0.0.1a8.dist-info/licenses/LICENSE
ctx_python-0.0.1a8.dist-info/RECORD
