Metadata-Version: 2.4
Name: ctx-python
Version: 0.0.1a8
Summary: A Python API client for US EPA's Computational Toxicology and Exposure APIs.
Project-URL: Repository, https://github.com/USEPA/ctx-python
Author-email: Katherine Phillips <phillips.katherine@epa.gov>
License-Expression: GPL-3.0-or-later
License-File: LICENSE
Classifier: Development Status :: 2 - Pre-Alpha
Classifier: Intended Audience :: Science/Research
Classifier: License :: OSI Approved :: GNU General Public License v3 or later (GPLv3+)
Classifier: Natural Language :: English
Classifier: Operating System :: OS Independent
Classifier: Programming Language :: Python :: 3.10
Classifier: Topic :: Scientific/Engineering :: Chemistry
Requires-Python: <4,>=3.10
Requires-Dist: pandas<3,>=2.1.4
Requires-Dist: python-dotenv<2,>=1.0.1
Requires-Dist: requests<3,>=2.31.0
